README.rst
setup.py
rhymediscovery/__init__.py
rhymediscovery/celex.py
rhymediscovery/evaluate_schemes.py
rhymediscovery/find_schemes.py
rhymediscovery.egg-info/PKG-INFO
rhymediscovery.egg-info/SOURCES.txt
rhymediscovery.egg-info/dependency_links.txt
rhymediscovery.egg-info/entry_points.txt
rhymediscovery.egg-info/requires.txt
rhymediscovery.egg-info/top_level.txt
rhymediscovery/data/schemes.json