Metadata-Version: 1.1
Name: rhymediscovery
Version: 0.2.1
Summary: Unsupervised Discovery of Rhyme Schemes
Home-page: https://github.com/jvamvas/rhymediscovery
Author: Jannis Vamvas
Author-email: jannis.vamvas@gmail.com
License: MIT
Platform: UNKNOWN
Classifier: Development Status :: 3 - Alpha
Classifier: Intended Audience :: Science/Research
Classifier: License :: OSI Approved :: MIT License
Classifier: Programming Language :: Python :: 2
Classifier: Programming Language :: Python :: 2.7
Classifier: Programming Language :: Python :: 3
Classifier: Programming Language :: Python :: 3.4
Classifier: Programming Language :: Python :: 3.5
